ominfra/.omlish-manifests.json
ominfra/README.md
ominfra/__about__.py
ominfra/__init__.py
ominfra/pyremote.py
ominfra/systemd.py
ominfra/threadworkers.py
ominfra/clouds/__init__.py
ominfra/clouds/aws/__init__.py
ominfra/clouds/aws/__main__.py
ominfra/clouds/aws/auth.py
ominfra/clouds/aws/cli.py
ominfra/clouds/aws/dataclasses.py
ominfra/clouds/aws/logs.py
ominfra/clouds/aws/metadata.py
ominfra/clouds/aws/instancetypes/__init__.py
ominfra/clouds/aws/instancetypes/__main__.py
ominfra/clouds/aws/instancetypes/cache.json.gz
ominfra/clouds/aws/instancetypes/cache.py
ominfra/clouds/aws/instancetypes/cli.py
ominfra/clouds/aws/journald2aws/__init__.py
ominfra/clouds/aws/journald2aws/__main__.py
ominfra/clouds/aws/journald2aws/cursor.py
ominfra/clouds/aws/journald2aws/driver.py
ominfra/clouds/aws/journald2aws/main.py
ominfra/clouds/aws/journald2aws/poster.py
ominfra/clouds/aws/models/__init__.py
ominfra/clouds/aws/models/base/__init__.py
ominfra/clouds/aws/models/base/_dataclasses.py
ominfra/clouds/aws/models/gen/__init__.py
ominfra/clouds/aws/models/gen/__main__.py
ominfra/clouds/aws/models/gen/cli.py
ominfra/clouds/aws/models/gen/gen.py
ominfra/clouds/aws/models/services/__init__.py
ominfra/clouds/aws/models/services/services.toml
ominfra/clouds/aws/models/services/ec2/__init__.py
ominfra/clouds/aws/models/services/ec2/_dataclasses.py
ominfra/clouds/aws/models/services/lambda_/__init__.py
ominfra/clouds/aws/models/services/lambda_/_dataclasses.py
ominfra/clouds/aws/models/services/rds/__init__.py
ominfra/clouds/aws/models/services/rds/_dataclasses.py
ominfra/clouds/aws/models/services/s3/__init__.py
ominfra/clouds/aws/models/services/s3/_dataclasses.py
ominfra/clouds/gcp/__init__.py
ominfra/clouds/gcp/api.py
ominfra/clouds/gcp/auth.py
ominfra/commands/__init__.py
ominfra/commands/runners.py
ominfra/commands/ssh.py
ominfra/journald/__init__.py
ominfra/journald/fields.py
ominfra/journald/genmessages.py
ominfra/journald/messages.py
ominfra/journald/tailer.py
ominfra-0.0.0.dev516.dist-info/licenses/LICENSE
ominfra-0.0.0.dev516.dist-info/METADATA
ominfra-0.0.0.dev516.dist-info/WHEEL
ominfra-0.0.0.dev516.dist-info/entry_points.txt
ominfra-0.0.0.dev516.dist-info/top_level.txt
ominfra-0.0.0.dev516.dist-info/RECORD
