Metadata-Version: 2.4
Name: ominfra
Version: 0.0.0.dev516
Summary: ominfra
Author: wrmsr
License-Expression: BSD-3-Clause
Project-URL: source, https://github.com/wrmsr/omlish
Classifier: Development Status :: 2 - Pre-Alpha
Classifier: Intended Audience :: Developers
Classifier: Operating System :: OS Independent
Classifier: Operating System :: POSIX
Classifier: Programming Language :: Python :: 3
Classifier: Programming Language :: Python :: 3.13
Requires-Python: >=3.13
License-File: LICENSE
Requires-Dist: omlish==0.0.0.dev516
Provides-Extra: all
Requires-Dist: omdev==0.0.0.dev516; extra == "all"
Requires-Dist: paramiko~=4.0; extra == "all"
Requires-Dist: asyncssh~=2.22; extra == "all"
Provides-Extra: omdev
Requires-Dist: omdev==0.0.0.dev516; extra == "omdev"
Provides-Extra: ssh
Requires-Dist: paramiko~=4.0; extra == "ssh"
Requires-Dist: asyncssh~=2.22; extra == "ssh"
Dynamic: license-file
